hoi4/__init__.py
hoi4/__main__.py
hoi4/binary.py
hoi4/data.py
hoi4/parse.py
hoi4/plain.py
hoi4.py-0.1.0.dist-info/LICENSE
hoi4.py-0.1.0.dist-info/METADATA
hoi4.py-0.1.0.dist-info/WHEEL
hoi4.py-0.1.0.dist-info/top_level.txt
hoi4.py-0.1.0.dist-info/RECORD
